LICENSE.txt
MANIFEST.in
README.rst
setup.cfg
setup.py
PyMysqlPool/__init__.py
PyMysqlPool.egg-info/PKG-INFO
PyMysqlPool.egg-info/SOURCES.txt
PyMysqlPool.egg-info/dependency_links.txt
PyMysqlPool.egg-info/requires.txt
PyMysqlPool.egg-info/top_level.txt
PyMysqlPool/constant/__init__.py
PyMysqlPool/constant/constant.py
PyMysqlPool/db_util/__init__.py
PyMysqlPool/db_util/mysql_pool.py
PyMysqlPool/db_util/mysql_util.py
PyMysqlPool/db_util/db_config/__init__.py
PyMysqlPool/db_util/db_config/example_config.py
PyMysqlPool/db_util/python_rf/__init__.py
PyMysqlPool/db_util/python_rf/pool_convertor.py
PyMysqlPool/example/__init__.py
PyMysqlPool/example/example_case.py
PyMysqlPool/example/example_thread.py
PyMysqlPool/log/logging.err
PyMysqlPool/mysql/__init__.py
PyMysqlPool/mysql/connector/__init__.py
PyMysqlPool/mysql/connector/abstracts.py
PyMysqlPool/mysql/connector/authentication.py
PyMysqlPool/mysql/connector/catch23.py
PyMysqlPool/mysql/connector/charsets.py
PyMysqlPool/mysql/connector/connection.py
PyMysqlPool/mysql/connector/connection_cext.py
PyMysqlPool/mysql/connector/constants.py
PyMysqlPool/mysql/connector/conversion.py
PyMysqlPool/mysql/connector/cursor.py
PyMysqlPool/mysql/connector/cursor_cext.py
PyMysqlPool/mysql/connector/custom_types.py
PyMysqlPool/mysql/connector/dbapi.py
PyMysqlPool/mysql/connector/dpooling.py
PyMysqlPool/mysql/connector/errorcode.py
PyMysqlPool/mysql/connector/errors.py
PyMysqlPool/mysql/connector/network.py
PyMysqlPool/mysql/connector/optionfiles.py
PyMysqlPool/mysql/connector/protocol.py
PyMysqlPool/mysql/connector/utils.py
PyMysqlPool/mysql/connector/version.py
PyMysqlPool/mysql/connector/django/__init__.py
PyMysqlPool/mysql/connector/django/base.py
PyMysqlPool/mysql/connector/django/client.py
PyMysqlPool/mysql/connector/django/compiler.py
PyMysqlPool/mysql/connector/django/creation.py
PyMysqlPool/mysql/connector/django/features.py
PyMysqlPool/mysql/connector/django/introspection.py
PyMysqlPool/mysql/connector/django/operations.py
PyMysqlPool/mysql/connector/django/schema.py
PyMysqlPool/mysql/connector/django/validation.py
PyMysqlPool/mysql/connector/fabric/__init__.py
