Metadata-Version: 1.1
Name: PyMysqlPool
Version: 1.0.8
Summary: python practical mysql pool -motivation from=>[lost connection to MySQL server during query]  base on mysql-connector support fixed | dynamic pool
Home-page: https://codeload.github.com/LuciferJack/python-mysql-pool/zip/master
Author: Lucifer Jack
Author-email: lujunxucuc@gmail.com
License: MIT
Keywords: mysql pool,queue,support list,dynamic pool,fixed pool
Platform: UNKNOWN
Classifier: Development Status :: 3 - Alpha
Classifier: Intended Audience :: Developers
Classifier: Topic :: Database :: Database Engines/Servers
Classifier: License :: OSI Approved :: MIT License
Classifier: Programming Language :: Python :: 2
Classifier: Programming Language :: Python :: 2.7
Classifier: Programming Language :: Python :: 3
Classifier: Programming Language :: Python :: 3.3
Classifier: Programming Language :: Python :: 3.4
Classifier: Programming Language :: Python :: 3.5
